diverse_seq/__init__.py
diverse_seq/_dvs.cpython-313-x86_64-linux-gnu.so
diverse_seq/cli.py
diverse_seq/cluster.py
diverse_seq/data/brca1.fa
diverse_seq/distance.py
diverse_seq/io.py
diverse_seq/records.py
diverse_seq/util.py
diverse_seq-2026.1.7.dist-info/METADATA
diverse_seq-2026.1.7.dist-info/WHEEL
diverse_seq-2026.1.7.dist-info/entry_points.txt
diverse_seq-2026.1.7.dist-info/licenses/LICENSE
diverse_seq-2026.1.7.dist-info/RECORD
