Metadata-Version: 2.4
Name: diverse_seq
Version: 2026.1.7
Classifier: Development Status :: 3 - Alpha
Classifier: Intended Audience :: Science/Research
Classifier: License :: OSI Approved :: BSD License
Classifier: Topic :: Scientific/Engineering :: Bio-Informatics
Classifier: Topic :: Software Development :: Libraries :: Python Modules
Classifier: Operating System :: OS Independent
Classifier: Programming Language :: Python :: 3.11
Classifier: Programming Language :: Python :: 3.12
Classifier: Programming Language :: Python :: 3.13
Classifier: Programming Language :: Python :: 3.14
Requires-Dist: attrs
Requires-Dist: click
Requires-Dist: cogent3>=2026.1.6a1
Requires-Dist: numpy
Requires-Dist: rich
Requires-Dist: scitrack
Requires-Dist: scikit-learn
Requires-Dist: cogapp ; extra == 'dev'
Requires-Dist: docformatter ; extra == 'dev'
Requires-Dist: flit ; extra == 'dev'
Requires-Dist: ruff==0.14.10 ; extra == 'dev'
Requires-Dist: diverse-seq[test] ; extra == 'dev'
Requires-Dist: diverse-seq[doc] ; extra == 'dev'
Requires-Dist: diverse-seq[extra] ; extra == 'doc'
Requires-Dist: mkdocs>=1.6.1 ; extra == 'doc'
Requires-Dist: markdown-exec[ansi]>=1.10.0 ; extra == 'doc'
Requires-Dist: mkdocs-jupyter>=0.25.1 ; extra == 'doc'
Requires-Dist: markdown>=3.7 ; extra == 'doc'
Requires-Dist: numpydoc ; extra == 'doc'
Requires-Dist: cogent3[extra] ; extra == 'extra'
Requires-Dist: ipykernel ; extra == 'extra'
Requires-Dist: ipython ; extra == 'extra'
Requires-Dist: ipywidgets ; extra == 'extra'
Requires-Dist: jupyter-client ; extra == 'extra'
Requires-Dist: jupyterlab ; extra == 'extra'
Requires-Dist: jupytext ; extra == 'extra'
Requires-Dist: kaleido ; extra == 'extra'
Requires-Dist: nbconvert>5.4 ; extra == 'extra'
Requires-Dist: nbformat ; extra == 'extra'
Requires-Dist: plotly ; extra == 'extra'
Requires-Dist: nox ; extra == 'test'
Requires-Dist: pytest ; extra == 'test'
Requires-Dist: pytest-cov ; extra == 'test'
Requires-Dist: maturin ; extra == 'test'
Provides-Extra: dev
Provides-Extra: doc
Provides-Extra: extra
Provides-Extra: test
License-File: LICENSE
Keywords: biology,genomics,statistics,phylogeny,evolution,bioinformatics
Author-email: Gavin Huttley <Gavin.Huttley@anu.edu.au>
Requires-Python: >=3.11, <3.15
Project-URL: Bug Tracker, https://github.com/HuttleyLab/DiverseSeq/issues
Project-URL: Documentation, https://diverse-seq.readthedocs.io/
Project-URL: Source Code, https://github.com/HuttleyLab/DiverseSeq/
